circlevis/__init__.py
circlevis/beatmap_info.py
circlevis/classifier.py
circlevis/clock.py
circlevis/controls.py
circlevis/interface.py
circlevis/palette.py
circlevis/player.py
circlevis/renderer.py
circlevis/replay_info.py
circlevis/runtime_tracker.py
circlevis/utils.py
circlevis/version.py
circlevis/visualizer.py
circlevis/visualizer_controls.py
circlevis/widgets.py
circlevis/resources/clipboard.svg
circlevis/resources/frame_back.png
circlevis/resources/frame_next.png
circlevis/resources/info.png
circlevis/resources/pause.png
circlevis/resources/play.png
circlevis/resources/play_normal.png
circlevis/resources/play_reverse.png
circlevis/resources/settings_wheel.png
circlevis/resources/speed_down.png
circlevis/resources/speed_up.png
circlevis-1.4.7.dist-info/LICENSE
circlevis-1.4.7.dist-info/METADATA
circlevis-1.4.7.dist-info/WHEEL
circlevis-1.4.7.dist-info/top_level.txt
circlevis-1.4.7.dist-info/RECORD
