Metadata-Version: 2.1
Name: circlevis
Version: 1.4.7
Summary: A Qt Widget for visualizing osu! beatmaps and replays.
Home-page: https://github.com/circleguard/circlevis
Download-URL: https://github.com/circleguard/circlevis/tarball/v1.4.7
Author: Liam DeVoe
Author-email: orionldevoe@gmail.com
Keywords: osu!,python,Qt
Classifier: Programming Language :: Python :: 3
Classifier: Intended Audience :: Developers
Classifier: Operating System :: OS Independent
License-File: LICENSE
Requires-Dist: circleguard (<6.0.0,>=5.2.3)
Requires-Dist: slider (>=0.4.0)
Requires-Dist: PyQt6
